README.md
setup.cfg
setup.py
env/__init__.py
env/lib/__init__.py
examples/__init__.py
examples/binding_example.py
examples/distributed_counter_example.py
examples/luggage_models.py
examples/quickstart_example.py
examples/relationship_example.py
examples/view_example.py
examples/city/__init__.py
examples/city/forms.py
examples/city/main.py
examples/city/mediators.py
examples/city/models.py
examples/city/tests.py
examples/city/views.py
examples/fluttergram/__init__.py
examples/fluttergram/domain_models/__init__.py
examples/fluttergram/domain_models/post.py
examples/fluttergram/domain_models/user.py
examples/fluttergram/tests/__init__.py
examples/fluttergram/tests/fixtures.py
examples/fluttergram/tests/test_delta_dav.py
examples/lc_engine/__init__.py
examples/lc_engine/fb-test/__init__.py
examples/lc_engine/fb-test/app.py
examples/lc_engine/fb-test/view.py
examples/lc_engine/fb-test/wsgi.py
examples/meeting_room/__init__.py
examples/meeting_room/graphql_quickstart.py
examples/meeting_room/quickstart.py
examples/meeting_room/domain_models/__init__.py
examples/meeting_room/domain_models/location.py
examples/meeting_room/domain_models/meeting.py
examples/meeting_room/domain_models/ticket.py
examples/meeting_room/domain_models/user.py
examples/meeting_room/tests/__init__.py
examples/meeting_room/tests/fixtures.py
examples/meeting_room/tests/test_dav.py
examples/meeting_room/tests/test_relationships.py
examples/meeting_room/tests/test_view_model.py
examples/meeting_room/view_models/__init__.py
examples/meeting_room/view_models/meeting_session.py
examples/meeting_room/view_models/user_view.py
examples/meeting_room/views/__init__.py
examples/meeting_room/views/graphql_view.py
examples/meeting_room/views/mediators.py
examples/meeting_room/views/meeting_session_ops.py
examples/meeting_room/views/rest_mediators.py
flask_boiler/__init__.py
flask_boiler/auth.py
flask_boiler/collection_mixin.py
flask_boiler/common.py
flask_boiler/config.py
flask_boiler/context.py
flask_boiler.egg-info/PKG-INFO
flask_boiler.egg-info/SOURCES.txt
flask_boiler.egg-info/dependency_links.txt
flask_boiler.egg-info/requires.txt
flask_boiler.egg-info/top_level.txt
