Metadata-Version: 2.1
Name: flask-boiler
Version: 0.0.2.dev19
Summary: Build reactive back end with ease 
Home-page: https://github.com/billyrrr/flask-boiler
Author: Bill Rao
Author-email: billrao@me.com
License: UNKNOWN
Keywords: firebase,firestore,ORM,flasgger,flask,backend,nosql,reactive,framework
Platform: UNKNOWN
Classifier: Development Status :: 4 - Beta
Classifier: Intended Audience :: Developers
Classifier: Programming Language :: Python :: 3.7
Classifier: Programming Language :: Python :: 3.8
Classifier: License :: OSI Approved :: MIT License
Classifier: Operating System :: OS Independent
